leap_uie/UIE.cpython-310-darwin.so
leap_uie/__init__.cpython-310-darwin.so
leap_uie/config_handler.cpython-310-darwin.so
leap_uie/event_handler.cpython-310-darwin.so
leap_uie/generation.cpython-310-darwin.so
leap_uie/generation_tf.cpython-310-darwin.so
leap_uie/logging_handler.cpython-310-darwin.so
leap_uie/objectives.cpython-310-darwin.so
leap_uie/objectives_tf.cpython-310-darwin.so
leap_uie/saliency.cpython-310-darwin.so
leap_uie/saliency_tf.cpython-310-darwin.so
leap_uie/transforms.cpython-310-darwin.so
leap_uie/transforms_tf.cpython-310-darwin.so
leap_uie/utils.cpython-310-darwin.so
leap_uie/vega_charts.cpython-310-darwin.so
py_package_robbiemccorkell-0.0.12.dist-info/LICENSE
py_package_robbiemccorkell-0.0.12.dist-info/METADATA
py_package_robbiemccorkell-0.0.12.dist-info/WHEEL
py_package_robbiemccorkell-0.0.12.dist-info/top_level.txt
py_package_robbiemccorkell-0.0.12.dist-info/RECORD
