Metadata-Version: 2.1
Name: py-package-robbiemccorkell
Version: 0.0.12
Summary: Leap Labs Universal Interpretability Engine
Home-page: https://www.leap-labs.com/
Author: Jessica Rumbelow
Author-email: jessica@leap-labs.com
License: Closed-source
License-File: LICENSE
Requires-Dist: tensorflow >=2.13.0
Requires-Dist: ipython >=8.14.0
Requires-Dist: pandas >=2.0.3
Requires-Dist: tqdm >=4.65.0
Requires-Dist: wandb >=0.15.4
